LICENSE
LICENSE.txt
MANIFEST.in
README.md
setup.cfg
setup.py
pydiv/__init__.py
pydiv/pydiv.py
pydiv/version.py
pydiv.egg-info/PKG-INFO
pydiv.egg-info/SOURCES.txt
pydiv.egg-info/dependency_links.txt
pydiv.egg-info/top_level.txt