Metadata-Version: 1.1
Name: pydiv
Version: 2.1
Summary: Gives the division forms for decimal numbers
Home-page: https://github.com/AnkanDas22/pydiv
Author: Ankan Das
Author-email: ankandas2222@gmail.com
License: UNKNOWN
Download-URL: https://github.com/AnkanDas22/pydiv/archive/2.0.tar.gz
Platform: UNKNOWN
